[
    {
        "name": "Mobisys 2025",
        "submission_deadline": "2024-12-09",
        "notification_date": "2025-03-07",
        "conference_dates": {
            "start": "2025-07-01",
            "end": "2025-07-02"
        },
        "location": "Anaheim, California, US",
        "link": "https://sigmobile.org/mobisys/2025/"
    },
    {
        "name": "MobiCom 2025 (Winter)",
        "submission_deadline": "2025-03-18",
        "notification_date": "2025-06-24",
        "conference_dates": {
            "start": "2024-04-15",
            "end": "2024-04-18"
        },
        "location": "Hong Kong, China",
        "link": "https://www.sigmobile.org/mobicom/2025/"
    },
    {
        "name": "SIGCOMM 2025",
        "submission_deadline": "2025-01-31",
        "notification_date": "2025-04-29",
        "conference_dates": {
            "start": "2025-09-08",
            "end": "2025-09-11"
        },
        "location": "Coimbra, Portugal",
        "link": "https://conferences.sigcomm.org/sigcomm/2025"
    }
]
